fava_dashboards/FavaDashboards.js
fava_dashboards/__init__.py
fava_dashboards/templates/FavaDashboards.html
fava_dashboards/templates/style.css
fava_dashboards-1.2.2.dist-info/METADATA
fava_dashboards-1.2.2.dist-info/WHEEL
fava_dashboards-1.2.2.dist-info/licenses/LICENSE.md
fava_dashboards-1.2.2.dist-info/RECORD
