Metadata-Version: 2.4
Name: fava-dashboards
Version: 1.2.2
Summary: Custom Dashboards for Beancount in Fava
Project-URL: Source, https://github.com/andreasgerstmayr/fava-dashboards
Project-URL: Issues, https://github.com/andreasgerstmayr/fava-dashboards/issues
Project-URL: Changelog, https://github.com/andreasgerstmayr/fava-dashboards/blob/main/CHANGELOG.md
Author-email: Andreas Gerstmayr <andreas@gerstmayr.me>
License: MIT License
License-File: LICENSE.md
Keywords: beancount,dashboards,fava
Classifier: Development Status :: 4 - Beta
Classifier: Intended Audience :: Financial and Insurance Industry
Classifier: Topic :: Office/Business :: Financial :: Accounting
Classifier: Topic :: Office/Business :: Financial :: Investment
Requires-Python: >=3.10
Requires-Dist: beanquery>=0.1.0
Requires-Dist: fava>=1.30.8
Requires-Dist: pyyaml>=6.0.1
